uncertainty_estimation/__init__.py
uncertainty_estimation/constants.py
uncertainty_estimation/uncertainty_estimation_models.py
uncertainty_estimation_models-0.1.0.dist-info/WHEEL
uncertainty_estimation_models-0.1.0.dist-info/METADATA
uncertainty_estimation_models-0.1.0.dist-info/RECORD
